README.md
setup.py
r2ai/__init__.py
r2ai/anthropic.py
r2ai/auto.py
r2ai/bubble.py
r2ai/code_block.py
r2ai/const.py
r2ai/index.py
r2ai/interpreter.py
r2ai/main.py
r2ai/message_block.py
r2ai/models.py
r2ai/pipe.py
r2ai/repl.py
r2ai/tab.py
r2ai/utils.py
r2ai/voice.py
r2ai.egg-info/PKG-INFO
r2ai.egg-info/SOURCES.txt
r2ai.egg-info/dependency_links.txt
r2ai.egg-info/entry_points.txt
r2ai.egg-info/requires.txt
r2ai.egg-info/top_level.txt