Metadata-Version: 2.1
Name: r2ai
Version: 0.7.0
Summary: Applying language models on radare2 for reverse engineering and fun purposes
Home-page: https://www.radare.org/
Author: pancake
Author-email: pancake@nopcode.org
Requires-Dist: rich
Requires-Dist: r2pipe
Requires-Dist: inquirer
Requires-Dist: llama-cpp-python
Requires-Dist: huggingface_hub
Requires-Dist: appdirs
Requires-Dist: unidecode
Requires-Dist: jsonref
Requires-Dist: transformers
Requires-Dist: pydantic
Requires-Dist: torch
